{
  "/.well-known/skill.md/route": "app/.well-known/skill.md/route.js",
  "/_global-error/page": "app/_global-error/page.js",
  "/_not-found/page": "app/_not-found/page.js",
  "/api/agent-auth/[[...fishnet-auth]]/route": "app/api/agent-auth/[[...fishnet-auth]]/route.js",
  "/api/agent-auth/protected/route": "app/api/agent-auth/protected/route.js",
  "/api/demo/solve/route": "app/api/demo/solve/route.js",
  "/api/health/route": "app/api/health/route.js",
  "/api/sessions/[sessionId]/state/route": "app/api/sessions/[sessionId]/state/route.js",
  "/api/sessions/join/route": "app/api/sessions/join/route.js",
  "/api/test/route": "app/api/test/route.js",
  "/demo/fishnet/page": "app/demo/fishnet/page.js",
  "/favicon.ico/route": "app/favicon.ico/route.js",
  "/page": "app/page.js",
  "/skill.md/route": "app/skill.md/route.js"
}